matrix_position/__init__.py
matrix_position/urls.py
matrix_position-0.0.5.dist-info/LICENSE
matrix_position-0.0.5.dist-info/METADATA
matrix_position-0.0.5.dist-info/WHEEL
matrix_position-0.0.5.dist-info/top_level.txt
matrix_position-0.0.5.dist-info/RECORD
