Metadata-Version: 2.1
Name: matrix-position
Version: 0.0.5
Summary: A package that express the data structure of matrix, and combined with the matrix, it can obtain the position and value around any two-dimensional coordinates.
Author-email: Jinghao <psymhmch@163.com>, LiuShuhua <492653598@qq.com>
Project-URL: Homepage, https://github.com/Zeaulo/matrix_position
Project-URL: Bug Tracker, https://github.com/Zeaulo/matrix_position/issues
Classifier: Programming Language :: Python :: 3
Classifier: License :: OSI Approved :: MIT License
Classifier: Operating System :: OS Independent
Requires-Python: >=3.7
License-File: LICENSE
